pybcpy/__init__.py
pybcpy/__main__.py
pybcpy/backup_file_info.py
pybcpy/diff_bak_copy.py
pybcpy/file_utils.py
pybcpy/print_utils.py
pybcpy/pybcpy.py
pybcpy/storage.py
pybcpy/tar_utils.py
pybcpy/pyacltk/__init__.py
pybcpy/pyacltk/__main__.py
pybcpy/pyacltk/acl.py
pybcpy/pyacltk/flat.py
pybcpy/pyacltk/repo.py
pybcpy/pyacltk/tree.py
pybcpy/pyusrgrptk/__init__.py
pybcpy/pyusrgrptk/__main__.py
pybcpy/pyusrgrptk/usrgrptk.py
pybcpy-0.0.17.dist-info/LICENSE
pybcpy-0.0.17.dist-info/METADATA
pybcpy-0.0.17.dist-info/WHEEL
pybcpy-0.0.17.dist-info/entry_points.txt
pybcpy-0.0.17.dist-info/top_level.txt
pybcpy-0.0.17.dist-info/RECORD
