Metadata-Version: 2.1
Name: pybcpy
Version: 0.0.17
Summary: pybcpy - backup copy - utility
Home-page: https://github.com/kr-g/pybcpy
Author: k.r. goger
Author-email: k.r.goger+pybcpy@gmail.com
License: UNKNOWN
Keywords: python backup file-copy file-backup diff-backup differential-backup acl groups
Platform: UNKNOWN
Classifier: Development Status :: 3 - Alpha
Classifier: Operating System :: POSIX :: Linux
Classifier: Operating System :: OS Independent
Classifier: Environment :: Console
Classifier: Intended Audience :: System Administrators
Classifier: Intended Audience :: Developers
Classifier: Intended Audience :: Information Technology
Classifier: Topic :: Utilities
Classifier: Topic :: System :: Archiving :: Backup
Classifier: Topic :: System :: Recovery Tools
Classifier: Programming Language :: Python :: 3
Classifier: License :: OSI Approved :: GNU Affero General Public License v3 or later (AGPLv3+)
Requires-Python: >=3.6
License-File: LICENSE
